rewet/Main_GUI.py
rewet/Project.py
rewet/Report_Reading.py
rewet/__init__.py
rewet/initial.py
rewet/repair.py
rewet/result.py
rewet/EnhancedWNTR/__init__.py
rewet/EnhancedWNTR/epanet/__init__.py
rewet/EnhancedWNTR/epanet/io.py
rewet/EnhancedWNTR/epanet/toolkit.py
rewet/EnhancedWNTR/epanet/Darwin/libepanet22_mod.dylib
rewet/EnhancedWNTR/epanet/Linux/libepanet22_mod.so
rewet/EnhancedWNTR/epanet/Windows/epanet22_mod.dll
rewet/EnhancedWNTR/morph/__init__.py
rewet/EnhancedWNTR/morph/link.py
rewet/EnhancedWNTR/network/__init__.py
rewet/EnhancedWNTR/network/model.py
rewet/EnhancedWNTR/sim/__init__.py
rewet/EnhancedWNTR/sim/epanet.py
rewet/EnhancedWNTR/sim/io.py
rewet/EnhancedWNTR/sim/results.py
rewet/EnhancedWNTR/sim/toolkit.py
rewet/GUI/Damage_Discovery_Designer.py
rewet/GUI/Damage_Discovery_Window.py
rewet/GUI/Damage_Tab_Designer.py
rewet/GUI/Hydraulic_Tab_Designer.py
rewet/GUI/Input_IO.py
rewet/GUI/Main_Help_Designer.py
rewet/GUI/Main_Help_Window.py
rewet/GUI/Map_Designer.py
rewet/GUI/MplWidget.py
rewet/GUI/Node_Damage_Discovery_Designer.py
rewet/GUI/Node_Damage_Model_Designer.py
rewet/GUI/Node_Damage_Model_Help_Designer.py
rewet/GUI/Node_Damage_Model_Help_Window.py
rewet/GUI/Node_Damage_Model_Window.py
rewet/GUI/Opening_Designer.py
rewet/GUI/Opening_Window.py
rewet/GUI/PP_Data_Tab_Designer.py
rewet/GUI/Pipe_Damage_Discovery_Designer.py
rewet/GUI/Pipe_Damage_Discovery_Window.py
rewet/GUI/Pipe_Damage_Model_Designer.py
rewet/GUI/Pipe_Damage_Model_Window.py
rewet/GUI/Pump_Damage_Discovery_Designer.py
rewet/GUI/REWET_Resource_rc.py
rewet/GUI/Restoration_Tab_Designer.py
rewet/GUI/Result_Designer.py
rewet/GUI/Run_Tab_Designer.py
rewet/GUI/Scenario_Dialog_Designer.py
rewet/GUI/Scenario_Dialog_Window.py
rewet/GUI/Simulation_Tab_Designer.py
rewet/GUI/Subsitute_Layer_Designer.py
rewet/GUI/Subsitute_Layer_Window.py
rewet/GUI/Symbology_Designer.py
rewet/GUI/Symbology_Window.py
rewet/GUI/Tank_Damage_Discovery_Designer.py
rewet/GUI/__init__.py
rewet/Input/GUI_Input_Interface.py
rewet-0.2.1a2.dist-info/LICENSE
rewet-0.2.1a2.dist-info/METADATA
rewet-0.2.1a2.dist-info/WHEEL
rewet-0.2.1a2.dist-info/top_level.txt
rewet-0.2.1a2.dist-info/RECORD
